{
    "type": "EmailAudience",
    "name": "APAC_BP00028_Nurture_Pre_Renewals",
    "description": "",
    "createdDate": "2025-09-09T20:24:08.93",
    "createdBy": "Julia Funk",
    "modifiedDate": "2025-09-09T20:40:22.21",
    "modifiedBy": "Julia Funk",
    "eventDefinitionKey": "DEAudience-5f40a8a2-2d99-e165-fd8f-2f4346718c7c",
    "sourceApplicationExtensionId": "97e942ee-6914-4d3d-9e52-37ecb71f79ed",
    "filterDefinitionTemplate": "",
    "iconUrl": "/images/icon-data-extension.svg",
    "arguments": {
        "serializedObjectType": 3,
        "criteria": "",
        "useHighWatermark": false
    },
    "configurationArguments": {},
    "metaData": {
        "scheduleState": "No Schedule",
        "criteriaDescription": null,
        "scheduleFlowMode": "runOnce",
        "runOnceScheduleMode": "onPublish"
    },
    "interactionCount": 1,
    "isVisibleInPicker": false,
    "category": "Audience",
    "publishedInteractionCount": 1,
    "disableDEDataLogging": false,
    "r__automation_key": "180ac8f4-8be1-4e93-9915-373779be3503"
}
