{
    "kind": "discovery#restDescription",
    "id": "hub:v1",
    "name": "hub",
    "version": "v1",
    "title": "Hub Service",
    "description": "",
    "protocol": "rest",
    "basePath": "hubservice",
    "methods": {
        "discovery": {
            "path": "rest",
            "httpMethod": "get",
            "description": "Discovery document",
            "parameters": {}
        },
        "getCampaign": {
            "path": "campaigns/{id}",
            "httpMethod": "get",
            "description": "Retrieve a Campaign",
            "parameters": {}
        },
        "getCampaignCollection": {
            "path": "campaigns",
            "httpMethod": "get",
            "description": "Retrieve a collection of Campaigns",
            "parameters": {}
        },
        "getCampaignCollectionForAnAsset": {
            "path": "campaigns/entity/{id}/type/{type}",
            "httpMethod": "get",
            "description": "Retrieve a collection of Campaigns for a given asset",
            "parameters": {
                "id": "String id of entity",
                "type": "Options: email, automation_definition, calendar_event, triggered, list, group, data_extension, sendable_custom_object, landing_page, sms_message, push_message"
            }
        },
        "createCampaign": {
            "path": "campaigns",
            "httpMethod": "post",
            "description": "Create a Campaign",
            "parameters": {
                "name": "Campaign name",
                "description": "Description of the Campaign",
                "campaignCode": "Unique string Id for the Campaign",
                "color": "Hex value for the Campaign color",
                "favorite": "Boolean for favorite Campaign"
            }
        },
        "updateCampaign": {
            "path": "campaigns/{id}",
            "httpMethod": "post",
            "description": "Update a Campaign",
            "parameters": {
                "name": "Campaign name",
                "description": "Description of the Campaign",
                "campaignCode": "Unique string Id for the Campaign",
                "color": "Hex value for the Campaign color",
                "favorite": "Boolean for favorite Campaign"
            }
        },
        "patchCampaign": {
            "path": "campaigns/{id}",
            "httpMethod": "patch",
            "description": "Update a Campaign",
            "parameters": {
                "name": "Campaign name",
                "description": "Description of the Campaign",
                "campaignCode": "Unique string Id for the Campaign",
                "color": "Hex value for the Campaign color",
                "favorite": "Boolean for favorite Campaign"
            }
        },
        "deleteCampaign": {
            "path": "campaigns/{id}",
            "httpMethod": "delete",
            "description": "Delete a Campaign",
            "parameters": {}
        },
        "associateAssetToCampaign": {
            "path": "campaigns/{id}/assets",
            "httpMethod": "post",
            "description": "Associate an asset or collection of assets to a Campaign",
            "parameters": {
                "ids": "String array of ids",
                "type": "Options: email, automation_definition, calendar_event, triggered, list, group, data_extension, sendable_custom_object, landing_page, sms_message, push_message"
            }
        },
        "unassociateAssetToCampaign": {
            "path": "campaigns/{id}/assets/{assetId}",
            "httpMethod": "delete",
            "description": "Unassociate an asset from a Campaign",
            "parameters": {}
        },
        "getCampaignAssetCollection": {
            "path": "campaigns/{id}/assets",
            "httpMethod": "get",
            "description": "Retrieve a collection of Campaign Assets",
            "parameters": {}
        },
        "getCampaignAsset": {
            "path": "campaigns/{id}/assets/{assetId}",
            "httpMethod": "get",
            "description": "Retrieve a Campaign Asset",
            "parameters": {}
        },
        "getApplicationExtensionCollection": {
            "path": "applicationextensions/{extensionTypeKey}/@me",
            "httpMethod": "get",
            "description": "Retrieve a collection of application extensions",
            "parameters": {}
        },
        "GetEmailPreviewByID": {
            "path": "guideServices/v1/emails/{id}/preview",
            "httpMethod": "post",
            "description": "Get a preview for an email by id.",
            "parameters": {}
        },
        "GetEmailPreviewByIDWithContact": {
            "path": "guideServices/v1/emails/{id}/contacts/{cid}/preview",
            "httpMethod": "post",
            "description": "Get a preview for an email by id using a specific contact.",
            "parameters": {}
        },
        "GetEmailPreviewByIDWithList": {
            "path": "guideServices/v1/emails/{id}/lists/{lid}/preview",
            "httpMethod": "post",
            "description": "Get a preview for an email by id using a specific list.",
            "parameters": {}
        },
        "GetEmailPreviewByIDWithListAndContact": {
            "path": "guideServices/v1/emails/{id}/lists/{lid}/contacts/{cid}/preview",
            "httpMethod": "post",
            "description": "Get a preview for an email by id using a specific list and contact.",
            "parameters": {}
        },
        "putDataExtensionRowByKey": {
            "path": "dataevents/key:{key}/rows/{primaryKeys}",
            "httpMethod": "put",
            "description": "Upserts a data extension row by key.",
            "parameters": {}
        },
        "putDataExtensionRowByID": {
            "path": "dataevents/{guid}/rows/{primaryKeys}",
            "httpMethod": "put",
            "description": "Upserts a data extension row by ID.",
            "parameters": {}
        },
        "putDataExtensionRowByKeyAsync": {
            "path": "dataeventsasync/key:{key}/rows/{primaryKeys}",
            "httpMethod": "put",
            "description": "Asynchronously upserts a data extension row by key.",
            "parameters": {}
        },
        "putDataExtensionRowByIDAsync": {
            "path": "dataeventsasync/{guid}/rows/{primaryKeys}",
            "httpMethod": "put",
            "description": "Asynchronously upserts a data extension row by ID.",
            "parameters": {}
        },
        "putIncrementColumnValueByID": {
            "path": "dataevents/{guid}/rows/{primaryKeys}/column/{column}/increment",
            "httpMethod": "put",
            "description": "Increments a column value by data extension ID.",
            "parameters": {}
        },
        "putIncrementColumnValueByKey": {
            "path": "dataevents/key:{key}/rows/{primaryKeys}/column/{column}/increment",
            "httpMethod": "put",
            "description": "Increments a column value by data extenstion external key.",
            "parameters": {}
        },
        "putIncrementColumnValueByIDAsync": {
            "path": "dataeventsasync/{guid}/rows/{primaryKeys}/column/{column}/increment",
            "httpMethod": "put",
            "description": "Asynchronously increments a column value by data extension ID.",
            "parameters": {}
        },
        "putIncrementColumnValueByKeyAsync": {
            "path": "dataeventsasync/key:{key}/rows/{primaryKeys}/column/{column}/increment",
            "httpMethod": "put",
            "description": "Asynchronously increments a column value by data extenstion external key.",
            "parameters": {}
        },
        "postDataExtensionRowsetByKey": {
            "path": "dataevents/key:{key}/rowset",
            "httpMethod": "post",
            "description": "Upserts a batch of data extensions rows by key.",
            "parameters": {}
        },
        "postDataExtensionRowsetByID": {
            "path": "dataevents/{guid}/rowset",
            "httpMethod": "post",
            "description": "Upserts a batch of data extension rows by ID.",
            "parameters": {}
        },
        "deleteDataExtensionRowsetByKey": {
            "path": "dataevents/key:{key}/rowset/delete",
            "httpMethod": "post",
            "description": "Deletes a batch of data extension rows by key.",
            "parameters": {}
        },
        "deleteDataExtensionRowsetByID": {
            "path": "dataevents/{guid}/rowset/delete",
            "httpMethod": "post",
            "description": "Deletes a batch of data extension rows by ID.",
            "parameters": {}
        },
        "postDataExtensionRowsetByKeyAsync": {
            "path": "dataeventsasync/key:{key}/rowset",
            "httpMethod": "post",
            "description": "Asynchronously upserts a batch of data extensions rows by key.",
            "parameters": {}
        },
        "deleteDataExtensionRowsetByKeyAsync": {
            "path": "dataeventsasync/key:{key}/rowset/delete",
            "httpMethod": "post",
            "description": "Asynchronously deletes a batch of data extensions rows by key.",
            "parameters": {}
        },
        "postDataExtensionRowsetByIDAsync": {
            "path": "dataeventsasync/{guid}/rowset",
            "httpMethod": "post",
            "description": "Asynchronously upserts a batch of data extension rows by ID.",
            "parameters": {}
        },
        "findTags": {
            "path": "tags",
            "httpMethod": "get",
            "description": "Retrieves all tags, or retrieves all tags with a name or description matching a given text fragment",
            "parameters": {}
        },
        "upsertTag": {
            "path": "tags/{name}",
            "httpMethod": "put",
            "description": "Upserts a tag with a given name and an optional description",
            "parameters": {
                "name": "The name of the tag"
            }
        },
        "mergeTags": {
            "path": "tags/{newName}/merge",
            "httpMethod": "post",
            "description": "Merges one or more tags into another tag",
            "parameters": {
                "newName": "The name of the destination tag"
            }
        },
        "batchAssociateTags": {
            "path": "objects/{objectTypeName}/tags",
            "httpMethod": "post",
            "description": "Associates batch tags and objects",
            "parameters": {
                "objectTypeName": "The tag object type"
            }
        },
        "batchDisassociateTags": {
            "path": "objects/{objectTypeName}/tags/delete",
            "httpMethod": "post",
            "description": "Disassociates batch tags and objects",
            "parameters": {
                "objectTypeName": "The tag object type"
            }
        },
        "getTagsByCampaign": {
            "path": "campaigns/{id}/tags",
            "httpMethod": "get",
            "description": "Retrieves all tags for a given campaign",
            "parameters": {
                "id": "The ID of the campaign"
            }
        },
        "associateTagsWithCampaign": {
            "path": "campaigns/{id}/tags",
            "httpMethod": "post",
            "description": "Associates tags to a given campaign",
            "parameters": {
                "id": "The ID of the campaign"
            }
        },
        "disassociateTagFromCampaign": {
            "path": "campaigns/{id}/tags/{tagName}",
            "httpMethod": "delete",
            "description": "Disassociates a given tag from a given campaign",
            "parameters": {
                "id": "The ID of the campaign"
            }
        },
        "getApproval": {
            "path": "approvals/{id}",
            "httpMethod": "get",
            "description": "Gets an approval by id",
            "parameters": {
                "id": "The ID of the approval"
            }
        },
        "getApprovalCollection": {
            "path": "approvals",
            "httpMethod": "get",
            "description": "Gets an a collection of approvals",
            "parameters": {}
        },
        "getApprovalRoleCollection": {
            "path": "approvals/{id}/roles",
            "httpMethod": "get",
            "description": "Gets a collection of roles for an approval item as well as users for each role",
            "parameters": {}
        },
        "deleteApproval": {
            "path": "approvals/{id}",
            "httpMethod": "delete",
            "description": "Deletes an approval by id",
            "parameters": {
                "id": "The ID of the approval"
            }
        },
        "updateApproval": {
            "path": "approvals/{id}",
            "httpMethod": "patch",
            "description": "Updates an approval",
            "parameters": {
                "id": "The ID of the approval"
            }
        },
        "createApproval": {
            "path": "approvals",
            "httpMethod": "post",
            "description": "Creates an an approval",
            "parameters": {}
        },
        "getApprovalAssetAbilities": {
            "path": "approvals/abilities/{assettype}/{assetid}",
            "httpMethod": "get",
            "description": "Gets approval asset abilities",
            "parameters": {
                "assettype": "Type of asset",
                "assetid": "asset id"
            }
        },
        "getApprovalObjectAbilities": {
            "path": "approvals/abilities",
            "httpMethod": "get",
            "description": "Gets approval object abilities",
            "parameters": {}
        },
        "getApprovalObjectAbilitiesByObjectTypeAndState": {
            "path": "approvals/workflows/{objectType}/states/{stateId}/abilities",
            "httpMethod": "get",
            "description": "Gets approval object abilities by object type and state",
            "parameters": {
                "objecttype": "Type of object",
                "stateId": "Workflow state"
            }
        },
        "getEmailApprovalSettings": {
            "path": "approvals/settings",
            "httpMethod": "get",
            "description": "Gets email approvals settings",
            "parameters": {}
        },
        "updateEmailApprovalSetting": {
            "path": "approvals/settings",
            "httpMethod": "patch",
            "description": "updates email approvals setting",
            "parameters": {}
        },
        "insertWorkflowStateApprovalObjectAbility": {
            "path": "approvals/workflows/{objectType}/states/{stateId}/abilities",
            "httpMethod": "post",
            "description": "Creates workflow state for approval object ability",
            "parameters": {
                "objecttype": "Type of object",
                "stateId": "Workflow state"
            }
        },
        "deleteWorkflowStateApprovalObjectAbility": {
            "path": "approvals/workflows/{objectType}/states/{stateId}/abilities/{abilityName}",
            "httpMethod": "delete",
            "description": "Deletes workflow state for approval object ability",
            "parameters": {
                "objecttype": "Type of object",
                "stateId": "Workflow state",
                "abilityName": "Ability name"
            }
        },
        "transitionWorkflowItem": {
            "path": "workflowitems/{workflowitemid}/transitions",
            "httpMethod": "post",
            "description": "Transition for workflow items",
            "parameters": {
                "workflowitemid": "ID for workflow item"
            }
        },
        "createWorkflowRoleInstanceUser": {
            "path": "workflowitems/{workflowitemid}/roles/{workflowroleinstanceid}/users",
            "httpMethod": "post",
            "description": "Adds a role to a user for a workflow item",
            "parameters": {
                "workflowitemid": "ID for workflow item",
                "workflowroleinstanceid": "Creates WorkflowRoleInstanceUser entity"
            }
        },
        "deleteWorkflowRoleInstanceUser": {
            "path": "workflowitems/{workflowitemid}/roles/{workflowroleinstanceid}/users/{userid}",
            "httpMethod": "delete",
            "description": "Deletes a role from a user for a workflow item",
            "parameters": {
                "workflowitemid": "ID for workflow item",
                "workflowroleinstanceid": "ID for workflowroleinstance",
                "userid": "user id"
            }
        },
        "createWorkflowTeam": {
            "path": "workflowteams",
            "httpMethod": "post",
            "description": "Creates workflow team",
            "parameters": {}
        },
        "deleteWorkflowTeam": {
            "path": "workflowteams/{id}",
            "httpMethod": "delete",
            "description": "Deletes workflow team",
            "parameters": {
                "id": "ID for workflow team"
            }
        },
        "updateWorkflowTeam": {
            "path": "workflowteams/{id}",
            "httpMethod": "patch",
            "description": "Updates workflow team",
            "parameters": {
                "id": "ID for workflow team"
            }
        },
        "getCollectionWorkflowTeam": {
            "path": "workflowteams/{objecttypename}",
            "httpMethod": "get",
            "description": "Gets a collection of workflow teams",
            "parameters": {
                "objecttypename": "Name of the object type"
            }
        },
        "getCollectionWorkflowTeamRoleUser": {
            "path": "workflowteams/{id}/roleusers",
            "httpMethod": "get",
            "description": "Gets a collection of role users for a workflow team",
            "parameters": {
                "id": "ID for workflow team"
            }
        },
        "addWorkflowTeamRoleUser": {
            "path": "workflowteams/{id}/roleusers",
            "httpMethod": "post",
            "description": "Creates role users for a workflow team",
            "parameters": {
                "id": "ID for workflow team"
            }
        },
        "removeWorkflowTeamRoleUser": {
            "path": "workflowteams/{id}/roleusers/{workflowteamroleuserid}",
            "httpMethod": "delete",
            "description": "Deletes a workflow team role user for a workflow team",
            "parameters": {
                "id": "ID for workflow team",
                "workflowteamroleuserid": "ID for role for a user for a workflow"
            }
        },
        "createApprovalComment": {
            "path": "approvals/comments",
            "httpMethod": "post",
            "description": "Creates approval comment",
            "parameters": {}
        },
        "updateApprovalComment": {
            "path": "approvals/comments/{id}",
            "httpMethod": "patch",
            "description": "Updates approval comment",
            "parameters": {
                "id": "ID for Approval comment"
            }
        },
        "deleteApprovalComment": {
            "path": "approvals/comments/{id}",
            "httpMethod": "delete",
            "description": "Deletes approval comment",
            "parameters": {
                "id": "ID for Approval comment"
            }
        },
        "getApprovalComment": {
            "path": "approvals/comments/{id}",
            "httpMethod": "get",
            "description": "Gets approval comment",
            "parameters": {
                "id": "ID for Approval comment"
            }
        },
        "getApprovalCommentCollection": {
            "path": "approvals/comments",
            "httpMethod": "get",
            "description": "Gets a collction of approval comments",
            "parameters": {}
        },
        "getWorkflowRoleCollection": {
            "path": "workflowobjecttypes/{workflowobjecttype}/roles",
            "httpMethod": "get",
            "description": "Gets a collection of roles in a workflow",
            "parameters": {}
        },
        "getApprovalCollectionV2": {
            "path": "approvals-v2",
            "httpMethod": "get",
            "description": "Gets an a collection of approvals",
            "parameters": {}
        },
        "getApprovalsV2": {
            "path": "approvals-v2/{id}",
            "httpMethod": "get",
            "description": "Get an approval item",
            "parameters": {}
        },
        "getApprovalsV2ByAssetID": {
            "path": "approvals-v2/assets/{id}",
            "httpMethod": "get",
            "description": "Get an approval item By AssetID",
            "parameters": {}
        },
        "createApprovalV2": {
            "path": "approvals-v2",
            "httpMethod": "post",
            "description": "Create an approval item",
            "parameters": {}
        },
        "updateApprovalV2": {
            "path": "approvals-v2/{id}",
            "httpMethod": "patch",
            "description": "Update an approval item",
            "parameters": {}
        },
        "deleteApprovalV2": {
            "path": "approvals-v2/{id}",
            "httpMethod": "delete",
            "description": "Delete an approval item",
            "parameters": {}
        },
        "getNestedTags": {
            "path": "nestedTags",
            "httpMethod": "get",
            "description": "get all nested Tags",
            "parameters": {}
        },
        "getNestedTagById": {
            "path": "nestedTags/{id}",
            "httpMethod": "get",
            "description": "get nested Tag by ID",
            "parameters": {}
        },
        "CreateNestedTag": {
            "path": "nestedTags",
            "httpMethod": "post",
            "description": "create a nested tag",
            "parameters": {}
        },
        "UpdateNestedTag": {
            "path": "nestedTags/{id}",
            "httpMethod": "put",
            "description": "update a nested tag",
            "parameters": {}
        },
        "PatchNestedTag": {
            "path": "nestedTags/{id}",
            "httpMethod": "patch",
            "description": "patch a nested tag",
            "parameters": {}
        },
        "DeleteNestedTag": {
            "path": "nestedTags/{id}",
            "httpMethod": "delete",
            "description": "delete a nested tag",
            "parameters": {}
        },
        "GetSchemaForContact": {
            "path": "contacts/schema",
            "httpMethod": "get",
            "description": "Retrieves a Schema for the 'Contact' Entity namespace",
            "parameters": {}
        },
        "Fetch AttributeGroupDefinition": {
            "path": "contacts/schema/attributeGroups/{definitionID}",
            "httpMethod": "get",
            "description": "Fetches a single Attribute Group Definition by definitionID",
            "parameters": {}
        },
        "Fetch AttributeGroupDefinitions": {
            "path": "contacts/schema/attributeGroups/",
            "httpMethod": "get",
            "description": "Fetches a list of Attribute Group Definitions for the given schema context.",
            "parameters": {}
        },
        "Fetch AttributeGroupDefinition DefinitionName": {
            "path": "contacts/schema/attributeGroups/{definitionID}/definitionName",
            "httpMethod": "get",
            "description": "Fetches the DefinitionName for the indicated AttributeGroup.",
            "parameters": {}
        },
        "Create Attribute Group Definition": {
            "path": "contacts/schema/attributeGroups/",
            "httpMethod": "post",
            "description": "Creates a new Attribute Group Definition",
            "parameters": {}
        },
        "Update Attribute Group Definition Name": {
            "path": "contacts/schema/attributeGroups/{definitionID}/definitionName",
            "httpMethod": "post",
            "description": "Updates the DefinitionName an Attribute Group",
            "parameters": {}
        },
        "Delete AttributeGroupDefinition": {
            "path": "contacts/schema/attributeGroups/{definitionID}",
            "httpMethod": "delete",
            "description": "Deletes the Attribute Group Definition indicated by definitionID",
            "parameters": {}
        },
        "Upsert Attribute Group Icon Key": {
            "path": "contacts/schema/attributeGroups/{definitionID}/iconKey",
            "httpMethod": "post",
            "description": "Upserts the IconKey of an Attribute Group Definition",
            "parameters": {}
        },
        "Fetch SetDefinition": {
            "path": "contacts/schema/setDefinitions/{definitionID}",
            "httpMethod": "get",
            "description": "Fetches a single Set Definition by definitionID",
            "parameters": {}
        },
        "Fetch SetDefinitions": {
            "path": "contacts/schema/setDefinitions",
            "httpMethod": "get",
            "description": "Fetches a list of Set Definitions for the current Schema Context",
            "parameters": {}
        },
        "Create a SetDefinition": {
            "path": "contacts/schema/setDefinitions",
            "httpMethod": "post",
            "description": "Creates a SetDefinition",
            "parameters": {}
        },
        "Delete a SetDefinition": {
            "path": "contacts/schema/setDefinitions/{definitionID}",
            "httpMethod": "delete",
            "description": "Deletes a SetDefinition",
            "parameters": {}
        },
        "Update a SetDefinition DefinitionName": {
            "path": "contacts/schema/setDefinitions/{definitionID}/definitionName",
            "httpMethod": "post",
            "description": "Updates a SetDefinition DefinitionName",
            "parameters": {}
        },
        "Update a SetDefinition isRoot property": {
            "path": "contacts/schema/setDefinitions/{definitionID}/isRoot",
            "httpMethod": "post",
            "description": "Updates a SetDefinition isRoot property",
            "parameters": {}
        },
        "Fetch Relationship": {
            "path": "contacts/schema/setDefinitions/{definitionID}/relationships/{relationshipID}",
            "httpMethod": "get",
            "description": "Fetch a single Relationship by relationshipID",
            "parameters": {}
        },
        "Create Relationship": {
            "path": "contacts/schema/setDefinitions/{definitionID}/relationships/",
            "httpMethod": "post",
            "description": "Creates a new Relationship",
            "parameters": {}
        },
        "Delete Relationship": {
            "path": "contacts/schema/setDefinitions/{definitionID}/relationships/{relationshipID}",
            "httpMethod": "delete",
            "description": "Deletes an existing Relationship",
            "parameters": {}
        },
        "Update Relationship": {
            "path": "contacts/schema/setDefinitions/{definitionID}/relationships/{relationshipID}",
            "httpMethod": "post",
            "description": "Updates a Relationship",
            "parameters": {}
        },
        "Update Relationship Items": {
            "path": "contacts/schema/setDefinitions/{definitionID}/relationships/{relationshipID}/items",
            "httpMethod": "post",
            "description": "Updates a Relationship's cardinality",
            "parameters": {}
        },
        "Update Relationship Attributes": {
            "path": "contacts/schema/setDefinitions/{definitionID}/relationships/{relationshipID}/attributes",
            "httpMethod": "post",
            "description": "Updates a Relationship's Attributes",
            "parameters": {}
        },
        "Fetch ImportHistory": {
            "path": "contacts/importhistory/{destinationID}/",
            "httpMethod": "get",
            "description": "Fetches ImportHistory by destinationID",
            "parameters": {}
        },
        "FetchDefaultAddressDefinitions": {
            "path": "contacts/schema/defaultAddresses",
            "httpMethod": "get",
            "description": "Fetches all Default Address Definitions",
            "parameters": {}
        },
        "FetchDefaultAddressDefinitionsByType": {
            "path": "contacts/schema/defaultAddresses/type/{addressType}",
            "httpMethod": "get",
            "description": "Fetches all Default Address Definitions filtered by type",
            "parameters": {}
        }
    },
    "key": "Hub"
}
