{
    "CustomerKey": "34FFB749-1266-497E-A750-0F6C95922D17",
    "Name": "APAC_MX0102_V2",
    "Description": "",
    "IsSendable": false,
    "IsTestable": false,
    "Fields": [
        {
            "Name": "Subscriber Key",
            "DefaultValue": "",
            "MaxLength": 50,
            "IsRequired": true,
            "IsPrimaryKey": false,
            "FieldType": "Text"
        },
        {
            "Name": "Email Address",
            "DefaultValue": "",
            "MaxLength": 254,
            "IsRequired": true,
            "IsPrimaryKey": false,
            "FieldType": "EmailAddress"
        }
    ],
    "r__folder_ContentType": "dataextension",
    "r__folder_Path": "Data Extensions/01_B2B/02_APAC/01_BAU",
    "c__retentionPolicy": "none"
}
