{
    "CustomerKey": "38F73CC2-0A39-400A-99A7-1E3F59481100",
    "Name": "MX_Excess_Licences",
    "Description": "",
    "IsSendable": true,
    "IsTestable": false,
    "SendableDataExtensionField": {
        "Name": "EmailAddress"
    },
    "SendableSubscriberField": {
        "Name": "Subscriber Key"
    },
    "Fields": [
        {
            "Name": "ContactFirstName",
            "DefaultValue": "",
            "MaxLength": 50,
            "IsRequired": false,
            "IsPrimaryKey": false,
            "FieldType": "Text"
        },
        {
            "Name": "ContactLastName",
            "DefaultValue": "",
            "MaxLength": 50,
            "IsRequired": false,
            "IsPrimaryKey": false,
            "FieldType": "Text"
        },
        {
            "Name": "AccountName",
            "DefaultValue": "",
            "MaxLength": 50,
            "IsRequired": true,
            "IsPrimaryKey": false,
            "FieldType": "Text"
        },
        {
            "Name": "TotalStudents",
            "DefaultValue": "",
            "MaxLength": 50,
            "IsRequired": true,
            "IsPrimaryKey": false,
            "FieldType": "Text"
        },
        {
            "Name": "RegisteredStudents",
            "DefaultValue": "",
            "MaxLength": 50,
            "IsRequired": true,
            "IsPrimaryKey": false,
            "FieldType": "Text"
        },
        {
            "Name": "ExcessStudentsNumber",
            "DefaultValue": "",
            "MaxLength": 50,
            "IsRequired": true,
            "IsPrimaryKey": false,
            "FieldType": "Text"
        },
        {
            "Name": "OpportunityOwner",
            "DefaultValue": "",
            "MaxLength": 50,
            "IsRequired": true,
            "IsPrimaryKey": false,
            "FieldType": "Text"
        },
        {
            "Name": "ContactLocale",
            "DefaultValue": "",
            "MaxLength": 50,
            "IsRequired": false,
            "IsPrimaryKey": false,
            "FieldType": "Text"
        },
        {
            "Name": "CID18",
            "DefaultValue": "",
            "MaxLength": 50,
            "IsRequired": false,
            "IsPrimaryKey": false,
            "FieldType": "Text"
        },
        {
            "Name": "EmailAddress",
            "DefaultValue": "",
            "MaxLength": 254,
            "IsRequired": true,
            "IsPrimaryKey": true,
            "FieldType": "EmailAddress"
        },
        {
            "Name": "Username",
            "DefaultValue": "",
            "MaxLength": 600,
            "IsRequired": false,
            "IsPrimaryKey": false,
            "FieldType": "Text"
        }
    ],
    "r__folder_ContentType": "dataextension",
    "r__folder_Path": "Data Extensions/01_B2B/04_GLOBAL/Adhoc Lists/FY25/AMER/SalesSupport/AMER_Excess_LIcences",
    "c__retentionPolicy": "none"
}
