{
    "CustomerKey": "516517DA-EB1D-43F0-87D1-3E8A94BE18B3",
    "Name": "AMER_ISTEResponses",
    "Description": "",
    "IsSendable": false,
    "IsTestable": false,
    "Fields": [
        {
            "Name": "id",
            "DefaultValue": "",
            "MaxLength": 255,
            "IsRequired": true,
            "IsPrimaryKey": true,
            "FieldType": "Text"
        }
    ],
    "r__folder_ContentType": "dataextension",
    "r__folder_Path": "Data Extensions/Interactive Content",
    "c__retentionPolicy": "none"
}
