{
    "CreatedDate": "2025-03-28T12:51:00",
    "ModifiedDate": "2025-03-28T12:51:00",
    "CustomerKey": 2582,
    "Name": "Peas & Eggs (reply to Maddie W)",
    "Description": "Peas & Eggs (reply to Maddie W)",
    "FromName": "3P Learning",
    "FromAddress": "reply@my.3plearning.com",
    "UseDefaultRMMRules": false,
    "AutoForwardToEmailAddress": "Maddie.Williams@3plearning.com",
    "AutoForwardToName": "Maddie Williams",
    "DirectForward": false,
    "AutoReply": false,
    "SenderHeaderEmailAddress": "",
    "SenderHeaderName": "",
    "FallbackFromAddress": "",
    "createdBy": "Charlotte Dillabough",
    "modifiedBy": "Charlotte Dillabough"
}
