{
    "CreatedDate": "2025-04-03T08:34:00",
    "ModifiedDate": "2025-04-14T09:30:00",
    "CustomerKey": 256772,
    "Name": "AMER_MX0067_WMD2025_J4_EDM3_E - 7f704cfcf1fc4d50b92afed487a797e9",
    "Description": "AMER_MX0067_WMD2025_J4_EDM3_E - 7f704cfcf1fc4d50b92afed487a797e9",
    "Keyword": "",
    "FromName": "Mathletics",
    "FromAddress": "mathletics@my.3plearning.com",
    "SuppressTracking": true,
    "TriggeredSendType": "Continuous",
    "TriggeredSendStatus": "Inactive",
    "Email": {
        "ID": 137498
    },
    "List": {
        "ID": 187
    },
    "AutoAddSubscribers": false,
    "AutoUpdateSubscribers": false,
    "BatchInterval": 0,
    "EmailSubject": "🎉 Congratulations to the World Math Day winners!",
    "DynamicEmailSubject": "🎉 Congratulations to the World Math Day winners!",
    "IsMultipart": true,
    "IsWrapped": false,
    "AllowedSlots": 0,
    "NewSlotTrigger": 0,
    "r__folder_Path": "HiddenCategory/HiddenJourneyBuilderSimulationTriggeredSends",
    "c__priority": "Medium",
    "r__sendClassification_key": 1078
}
