{
    "customerKey": "1e7a91ce-c9f1-48eb-97bb-348ea3c41fe7",
    "assetType": {
        "name": "jpg",
        "displayName": "Image"
    },
    "fileProperties": {
        "fileName": "MX2304272203_AU_B2B_AVATAR_TEASER_RELEASE_ANNOUNCEMENT_HERO_BANNER_MX_580X220_SH.jpg",
        "extension": "jpg",
        "fileSize": 131814,
        "fileCreatedDate": "2023-05-11T22:24:17.5089791-06:00",
        "width": 580,
        "height": 220,
        "publishedURL": "https://image.my.3plearning.com/lib/fe3211717d640479701476/m/2/435a554c-8ef5-4194-ae25-998ff0924f6e.jpg"
    },
    "name": "MX2304272203_AU_B2B_AVATAR_TEASER_RELEASE_ANNOUNCEMENT_HERO_BANNER_MX_580X220_SH.jpg",
    "createdDate": "2023-05-11T22:24:17.51-06:00",
    "createdBy": {
        "email": "jenny.cheng@3plearning.com",
        "name": "Jenny Cheng"
    },
    "modifiedDate": "2023-05-12T02:54:05.173-06:00",
    "modifiedBy": {
        "name": "7acbd619-3f8e-4024-a2f2-76303f8a5712 app user"
    },
    "status": {
        "name": "Published"
    },
    "tags": [
        "1785",
        "1778",
        "1840",
        "3316"
    ],
    "availableViews": [],
    "modelVersion": 2,
    "r__folder_Path": "Content Builder/B2C/02_ASSETS/01_IMAGES/Hero Images"
}
