{
    "customerKey": "3fe0a8a2-55ed-467d-b014-70976e5f8d59",
    "assetType": {
        "name": "zip",
        "displayName": "Archive"
    },
    "fileProperties": {
        "fileName": "Copy of Sample EDM Banner_2.zip",
        "extension": "zip",
        "fileSize": 533760,
        "fileCreatedDate": "2025-01-08T09:01:16.0552577-06:00",
        "publishedURL": "https://image.my.3plearning.com/lib/fe3211717d640479701476/m/1/2ed9cc3d-b6f7-41da-a079-eb72a49d52db.zip"
    },
    "name": "Copy of Sample EDM Banner_2.zip",
    "createdDate": "2025-01-08T09:01:16.057-06:00",
    "createdBy": {
        "email": "lara.tetlow@3plearning.com",
        "name": "Lara Tetlow"
    },
    "modifiedDate": "2025-01-08T09:01:16.057-06:00",
    "modifiedBy": {
        "email": "lara.tetlow@3plearning.com",
        "name": "Lara Tetlow"
    },
    "status": {
        "name": "Published"
    },
    "availableViews": [],
    "modelVersion": 2,
    "r__folder_Path": "Content Builder/01_EMAILS/01_B2B/00_BAU/01_RE/02_EMEA/EMEA_RE0073_WorldBookDay2025 - Journey 1"
}
