{
    "type": "EmailAudience",
    "name": "AMER_RE0124_ReggiesReadathonFY25_MXCX - PROMO - EM2 (US) ",
    "description": "",
    "createdDate": "2025-02-04T08:46:57.54",
    "createdBy": "Kelly Sykes",
    "modifiedDate": "2025-02-04T08:47:38.297",
    "modifiedBy": "Kelly Sykes",
    "eventDefinitionKey": "DEAudience-2b9e6ab9-78ea-c0ea-718d-e2fdf4c5ff46",
    "sourceApplicationExtensionId": "97e942ee-6914-4d3d-9e52-37ecb71f79ed",
    "filterDefinitionTemplate": "",
    "iconUrl": "/images/icon-data-extension.svg",
    "arguments": {
        "serializedObjectType": 3,
        "criteria": "",
        "useHighWatermark": false
    },
    "configurationArguments": {},
    "metaData": {
        "scheduleState": "No Schedule",
        "criteriaDescription": "",
        "scheduleFlowMode": "runOnce",
        "runOnceScheduleMode": "onPublish"
    },
    "interactionCount": 1,
    "isVisibleInPicker": false,
    "category": "Audience",
    "publishedInteractionCount": 1,
    "disableDEDataLogging": false,
    "r__automation_key": "b265584c-8f47-43fe-a4f8-b619e3e04e68"
}
