{
    "customerKey": "15726DA0-3EA5-4FA5-B797-B2D95B5104D9",
    "assetType": {
        "name": "landingpage",
        "displayName": "Landing Page"
    },
    "name": "0001_jobTitleValidator_OLD",
    "owner": {
        "email": "stephan.peniguel@3plearning.com",
        "name": "Stephan Peniguel"
    },
    "createdDate": "2024-04-29T08:16:27.607-06:00",
    "createdBy": {
        "email": "stephan.peniguel@3plearning.com",
        "name": "Stephan Peniguel"
    },
    "modifiedDate": "2024-04-29T08:16:27.607-06:00",
    "modifiedBy": {
        "email": "stephan.peniguel@3plearning.com",
        "name": "Stephan Peniguel"
    },
    "memberId": 518004506,
    "status": {
        "name": "Draft"
    },
    "meta": {
        "cloudPages": {
            "c__published": false
        }
    },
    "modelVersion": 2,
    "r__folder_Path": "CloudPages/Common"
}
