{
    "CreatedDate": "2025-03-19T14:45:00",
    "ModifiedDate": "2025-03-20T06:50:00",
    "CustomerKey": 255870,
    "Name": "EM5_Early Learning - 6d8870c540e94291ae1cee1af1ee9762",
    "Description": "EM5_Early Learning - b405e7507217452785ca8008d59f2e8b",
    "Keyword": "",
    "FromName": "3P Learning",
    "FromAddress": "reply@my.3plearning.com",
    "SuppressTracking": true,
    "TriggeredSendType": "Continuous",
    "TriggeredSendStatus": "Inactive",
    "Email": {
        "ID": 135810
    },
    "List": {
        "ID": 187
    },
    "AutoAddSubscribers": false,
    "AutoUpdateSubscribers": false,
    "BatchInterval": 0,
    "EmailSubject": "What’s Your Early Learning Strategy for This Year?",
    "DynamicEmailSubject": "What’s Your Early Learning Strategy for This Year?",
    "IsMultipart": true,
    "IsWrapped": false,
    "AllowedSlots": 0,
    "NewSlotTrigger": 0,
    "r__folder_Path": "HiddenCategory/HiddenJourneyBuilderSimulationTriggeredSends",
    "c__priority": "Medium",
    "r__sendClassification_key": 1097
}
